simple_file_cryptography/__about__.py
simple_file_cryptography/__init__.py
simple_file_cryptography/__main__.py
simple_file_cryptography/crypto_utility.py
simple_file_cryptography/gui.py
simple_file_cryptography/mode.py
simple_file_cryptography/py.typed
simple_file_cryptography-0.0.2.dist-info/METADATA
simple_file_cryptography-0.0.2.dist-info/WHEEL
simple_file_cryptography-0.0.2.dist-info/licenses/LICENSE.txt
simple_file_cryptography-0.0.2.dist-info/RECORD
